CHANGES.txt
LICENSE.txt
MANIFEST.in
README.txt
setup.py
restful_client/__init__.py
restful_client/rest_client.py
restful_client.egg-info/PKG-INFO
restful_client.egg-info/SOURCES.txt
restful_client.egg-info/dependency_links.txt
restful_client.egg-info/requires.txt
restful_client.egg-info/top_level.txt