Metadata-Version: 1.0
Name: restful-client
Version: 0.1
Summary: An asynchronous RESTful client library.
Home-page: UNKNOWN
Author: Benjamin Scherrey
Author-email: scherrey@proteus-tech.com
License: See LICENSE.txt
Platform: UNKNOWN
